pytoml_config/__init__.py
pytoml_config/__version__.py
pytoml_config/configuration.py
pytoml_config-0.1.0.dist-info/LICENSE
pytoml_config-0.1.0.dist-info/METADATA
pytoml_config-0.1.0.dist-info/WHEEL
pytoml_config-0.1.0.dist-info/top_level.txt
pytoml_config-0.1.0.dist-info/RECORD
