Metadata-Version: 2.1
Name: pytoml-config
Version: 0.1.0
Summary: Easy TOML configuration file integration
Home-page: https://github.com/newvicx/pytoml_config
Author: Chris Newville
Author-email: chrisnewville1396@gmail.com
License: MIT
Project-URL: Changelog, https://github.com/newvicx/pytoml_config/blob/master/CHANGELOG.md
Project-URL: Source, https://github.com/newvicx/pytoml_config
Platform: UNKNOWN
Classifier: Development Status :: 4 - Beta
Classifier: Environment :: Web Environment
Classifier: Intended Audience :: Developers
Classifier: License :: OSI Approved :: MIT License
Classifier: Operating System :: Microsoft :: Windows
Classifier: Topic :: Internet :: WWW/HTTP
Classifier: Framework :: AsyncIO
Classifier: Programming Language :: Python :: 3
Requires-Python: >=3.6
License-File: LICENSE
Requires-Dist: toml (>=0.10.2)
Requires-Dist: python-box (>=6.0.2)
Requires-Dist: python-dotenv (>=0.20.0)
Requires-Dist: flatten-dict (>=0.4.2)
